test_code.py
G31_thermometry/G31_thermometry.py
G31_thermometry/__init__.py
G31_thermometry-1.0.1.dist-info/METADATA
G31_thermometry-1.0.1.dist-info/WHEEL
G31_thermometry-1.0.1.dist-info/top_level.txt
G31_thermometry-1.0.1.dist-info/RECORD
