Metadata-Version: 2.1
Name: G31_thermometry
Version: 1.0.1
Summary: A Python package useful to convert thermometer voltage to temperature
Author-email: federico-cacciotti <federico.cacciotti@roma1.infn.it>
Project-URL: Homepage, https://github.com/federico-cacciotti/G31_thermometry
Classifier: Programming Language :: Python :: 3
Classifier: License :: OSI Approved :: MIT License
Classifier: Operating System :: OS Independent
Requires-Python: >=3.10.5
